{
    "round": "1",
    "all": [
        {
            "init": "2",
            "name": "Гатц",
            "player": "true",
            "surprise": "false"
        },
        {
            "init": "3",
            "name": "Эльза",
            "player": "true",
            "surprise": "false"
        },
        {
            "init": "4",
            "name": "Эмбер",
            "player": "true",
            "surprise": "true"
        },
        {
            "init": "5",
            "name": "Сок",
            "player": "true",
            "surprise": "false"
        },
        {
            "init": "6",
            "name": "Абатор",
            "player": "false",
            "surprise": "true"
        },
        {
            "init": "7",
            "name": "гоблинс",
            "player": "false",
            "surprise": "true"
        },
        {
            "init": "8",
            "name": "каракатица",
            "player": "false",
            "surprise": "true"
        }
    ],
    "try": "2",
    "next": "8"
}